csobclient/__init__.py
csobclient/v19/__init__.py
csobclient/v19/cart.py
csobclient/v19/client.py
csobclient/v19/currency.py
csobclient/v19/customer/__init__.py
csobclient/v19/customer/account.py
csobclient/v19/customer/data.py
csobclient/v19/customer/login.py
csobclient/v19/dttm.py
csobclient/v19/fields.py
csobclient/v19/http/__init__.py
csobclient/v19/http/client.py
csobclient/v19/http/requests_client.py
csobclient/v19/key.py
csobclient/v19/merchant.py
csobclient/v19/order/__init__.py
csobclient/v19/order/address.py
csobclient/v19/order/data.py
csobclient/v19/order/delivery.py
csobclient/v19/payment.py
csobclient/v19/signature.py
csobclient/v19/webpage.py
csobclient-0.4.1.dist-info/LICENSE
csobclient-0.4.1.dist-info/METADATA
csobclient-0.4.1.dist-info/WHEEL
csobclient-0.4.1.dist-info/RECORD
